deepview_converter-3.0.2.dist-info/licenses/LICENSE.txt
deepview_rtm/__init__.py
deepview_rtm/__main__.py
deepview_rtm/calc_shapes.py
deepview_rtm/cudnn_weights_converter.py
deepview_rtm/exporter_v1.py
deepview_rtm/onnx_importer.py
deepview_rtm/optimizer.py
deepview_rtm/rtm_importer.py
deepview_rtm/tensorflow_importer.py
deepview_rtm/tflite_importer.py
deepview_rtm/toco_from_protos.py
deepview_rtm/utils.py
deepview_rtm/converter/__init__.py
deepview_rtm/converter/abstract_graph.py
deepview_rtm/converter/plugin_api/__init__.py
deepview_rtm/converter/plugin_api/dataset.py
deepview_rtm/converter/plugin_api/dataset_interface.py
deepview_rtm/converter/plugin_api/datasets/__init__.py
deepview_rtm/converter/plugin_api/datasets/core.py
deepview_rtm/converter/plugin_api/datasets/classification/__init__.py
deepview_rtm/converter/plugin_api/datasets/classification/image/__init__.py
deepview_rtm/converter/plugin_api/datasets/detection/__init__.py
deepview_rtm/converter/plugin_api/datasets/detection/boxes/__init__.py
deepview_rtm/onnx/__init__.py
deepview_rtm/onnx/onnx_ml_pb2.py
deepview_rtm/tensorflow/__init__.py
deepview_rtm/tflite/AbsOptions.py
deepview_rtm/tflite/ActivationFunctionType.py
deepview_rtm/tflite/AddNOptions.py
deepview_rtm/tflite/AddOptions.py
deepview_rtm/tflite/ArgMaxOptions.py
deepview_rtm/tflite/ArgMinOptions.py
deepview_rtm/tflite/BatchMatMulOptions.py
deepview_rtm/tflite/BatchToSpaceNDOptions.py
deepview_rtm/tflite/BidirectionalSequenceLSTMOptions.py
deepview_rtm/tflite/BidirectionalSequenceRNNOptions.py
deepview_rtm/tflite/BroadcastToOptions.py
deepview_rtm/tflite/Buffer.py
deepview_rtm/tflite/BuiltinOperator.py
deepview_rtm/tflite/BuiltinOptions.py
deepview_rtm/tflite/CallOnceOptions.py
deepview_rtm/tflite/CallOptions.py
deepview_rtm/tflite/CastOptions.py
deepview_rtm/tflite/CombinerType.py
deepview_rtm/tflite/ConcatEmbeddingsOptions.py
deepview_rtm/tflite/ConcatenationOptions.py
deepview_rtm/tflite/Conv2DOptions.py
deepview_rtm/tflite/CosOptions.py
deepview_rtm/tflite/CumsumOptions.py
deepview_converter-3.0.2.dist-info/METADATA
deepview_converter-3.0.2.dist-info/WHEEL
deepview_converter-3.0.2.dist-info/entry_points.txt
deepview_converter-3.0.2.dist-info/top_level.txt
deepview_converter-3.0.2.dist-info/RECORD
