Metadata-Version: 2.4
Name: deepview-converter
Version: 3.0.2
Summary: DeepViewRT Converter
Requires-Python: >=3.8
License-File: LICENSE.txt
Requires-Dist: deepview-rt>=2.6.3
Requires-Dist: networkx==3.1
Requires-Dist: flatbuffers==25.9.23
Requires-Dist: pillow==10.4.0
Requires-Dist: protobuf==3.20.3
Dynamic: license-file
